<?xml version="1.0" encoding="UTF-8"?>
<SlimOTA xmlns:xsi="http://www.w3.org/2001/XMLSchema-instance" xsi:noNamespaceSchemaLocation="ota.xsd">
    <Stable>
        <ja3gxx>
            <Filename>RR-N-v5.8.4-20170812-ja3gxx-Official.zip</Filename>
            <LastestStableUrl
                id="lasteststable"
                title="Lastest stable build"
                description="Latest stable Resurrection Remix build">https://drive.google.com/open?id=0B3-YioqZRf1RZHU5MjhzVWVYTlk</LastestStableUrl>
            <OldStableUrl
                id="oldstable"
                title="Old stable builds"
                description="Download old stable Resurrection Remix builds">https://drive.google.com/open?id=0B3-YioqZRf1RX1g0NkRyekw0Ym8</OldStableUrl>
            <LastestTestUrl
                id="lastesttest"
                title="Lastest test build"
                description="Download lastest Resurrection Remix test build">https://drive.google.com/open?id=0B3-YioqZRf1RRXZZdVgwSHFqTnc</LastestTestUrl>
            <OldtestUrl
		id="oldtest"
		title="Old test builds"
		description="Download old Resurrection Remix test builds">https://drive.google.com/open?id=0B3-YioqZRf1ReFI0UFV6WFBmdDg</OldtestUrl>
	    <GappsUrl
                id="gapps"
                title="OpenGApps"
                description="Download Open Gapps">http://opengapps.org/</GappsUrl>
	    <ChangelogRRUrl
		id="changelogrr"
		title="Changelog for Resurrection Remix"
		description="View changes in Resurrection Remix ROM">https://github.com/ResurrectionRemix/android_vendor_resurrection/blob/nougat/CHANGELOG.mkdn</ChangelogRRUrl>
	    <ChangelogLOSUrl
                id="changeloglos"
                title="Changelog for Lineage base"
                description="View changes in Lineage base">https://github.com/exynos5410/weekly_ota/blob/cm-14.1/CHANGELOG.md</ChangelogLOSUrl>
            <FixnappsUrl
		 id="fixnapps"
		 title="Some fix and apps for RR"
		 description="Download fix and apps for Resurrection Remix">https://drive.google.com/open?id=0B3-YioqZRf1RT2g1TVZOQzYxYlk</FixnappsUrl>
	    <XDAUrl
            	id="XDA"
            	title="XDA Thread"
            	description="Visit Resurrection Remix for i9500 XDA thread">https://forum.xda-developers.com/galaxy-s4/i9500-develop/resurrection-remix-n-t3650856</XDAUrl>
	</ja3gxx>
    </Stable>
</SlimOTA>
